Metadata-Version: 2.1
Name: soda-core-db2
Version: 3.5.6
License-File: LICENSE
Requires-Dist: soda-core==3.5.6
Requires-Dist: ibm-db==3.2.3
